bceauth/__init__.py
bceauth/auth.py
bceauth/utils.py
tests/__init__.py
tests/test_auth.py
tests/test_utils.py
baidu_bce_auth-0.0.5.dist-info/LICENSE
baidu_bce_auth-0.0.5.dist-info/METADATA
baidu_bce_auth-0.0.5.dist-info/WHEEL
baidu_bce_auth-0.0.5.dist-info/top_level.txt
baidu_bce_auth-0.0.5.dist-info/RECORD
