Metadata-Version: 2.1
Name: baidu-bce-auth
Version: 0.0.5
Summary: 帮助你生成百度云 API 的鉴权认证字符串(Authorization header)
Home-page: https://github.com/HuangShaoyan/baidu-bce-auth
Author: huangshaoyan
Author-email: huangshaoyan1982@gmail.com
License: UNKNOWN
Platform: UNKNOWN
Classifier: Programming Language :: Python :: 3.6
Classifier: Programming Language :: Python :: 3.7
Classifier: Programming Language :: Python :: 3.8
Classifier: Development Status :: 3 - Alpha
Classifier: License :: OSI Approved :: Apache Software License
Classifier: Operating System :: OS Independent
Classifier: Typing :: Typed
Requires-Python: >=3.6
